{
    "CPU": {
        "HX": "属于高功耗处理器，性能强劲但发热大，续航较短，适合由于固定插电使用的同学。",
        "V": "Ultra 200V 系列，主打极致续航和静音，图形性能不错，适合经常背电脑上课且不玩大型游戏的同学。",
        "H": "标压处理器，兼顾性能与功耗，是全能本和轻薄本的首选。",
        "Ryzen": "AMD 处理器多核性价比极高，适合预算有限但需要高性能渲染或多任务处理的同学。"
    },
    "RAM": {
        "16GB": "当前主流入门配置，能满足办公和轻度编程。如果你要开很多网页或跑虚拟机，建议后续升级或选32G。",
        "32GB": "生产力黄金配置。传媒剪辑、重度编程、多开虚拟机建议一步到位选32G。",
        "24GB": "部分新机型的奇葩配置，通常是单通道或不对称双通道，性能略受限但容量够用。"
    },
    "GPU": {
        "RTX 5060": "2026年主流游戏显卡，支持光追和AI超分，可以流畅运行绝大多数3A大作。",
        "Intel Arc": "Intel 核显/独显，视频编解码能力极强，非常适合剪辑视频，但游戏驱动兼容性略逊于NVIDIA。",
        "Radeon": "AMD 核显，性能足以应付网游（如LOL、CS2），省电且性价比高。",
        "UHD": "入门核显，仅限办公看剧，千万不要用来跑 3A 游戏。"
    }
}
